minvr3/__init__.py
minvr3/minvr3_net.py
minvr3/vr_event.py
minvr3-2023.8.0.dist-info/LICENSE
minvr3-2023.8.0.dist-info/METADATA
minvr3-2023.8.0.dist-info/WHEEL
minvr3-2023.8.0.dist-info/entry_points.txt
minvr3-2023.8.0.dist-info/top_level.txt
minvr3-2023.8.0.dist-info/RECORD
