Metadata-Version: 2.1
Name: minvr3
Version: 2023.8.0
Summary: Python client and server for MinVR3
Author-email: UMN Interactive Visualization Lab <ivlab-admin@umn.edu>
Project-URL: Homepage, https://ivlab.cs.umn.edu
Classifier: Programming Language :: Python :: 3
Classifier: Operating System :: OS Independent
Requires-Python: >=3.7
License-File: LICENSE
